src/__init__.py
src/core/__init__.py
src/core/LLM/__init__.py
src/core/LLM/cerebras_inference.py
src/kite_exclusive/__init__.py
src/kite_exclusive/commit_splitter/__init__.py
src/kite_exclusive/commit_splitter/prompts/prompt1.md
src/kite_exclusive/commit_splitter/services/__init__.py
src/kite_exclusive/commit_splitter/services/voyage_service.py
src/kite_exclusive/resolve_conflicts/__init__ copy.py
src/kite_exclusive/resolve_conflicts/__init__.py
src/kite_exclusive/resolve_conflicts/core.py
src/kite_exclusive/resolve_conflicts/morph_service.py
src/mcp/__init__.py
src/mcp/app.py
src/merge_conflicts/__init__.py
src/merge_conflicts/text_conflict.py
glide_mcp-0.1.23.dist-info/METADATA
glide_mcp-0.1.23.dist-info/WHEEL
glide_mcp-0.1.23.dist-info/entry_points.txt
glide_mcp-0.1.23.dist-info/licenses/LICENSE
glide_mcp-0.1.23.dist-info/RECORD
