Metadata-Version: 2.4
Name: glide-mcp
Version: 0.1.23
Summary: mcp server that saves you from git troubles
License-File: LICENSE
Requires-Python: >=3.13
Requires-Dist: black>=25.9.0
Requires-Dist: cerebras-cloud-sdk>=1.56.1
Requires-Dist: fastmcp>=2.12.5
Requires-Dist: google-generativeai>=0.8.0
Requires-Dist: helix-py>=0.2.30
Requires-Dist: numpy>=2.3.4
Requires-Dist: ollama>=0.6.0
Requires-Dist: openai>=2.6.0
Requires-Dist: protobuf>=6.33.0
Requires-Dist: python-dotenv>=1.1.1
Requires-Dist: twine>=6.2.0
Requires-Dist: voyageai>=0.3.5
